{
	"cat" : {
		"pos": [0.5, 15],
		"ret_pos": [31.5,13]
	},
	"doors": [{"width": 1, "height": 4, "pos": [28, 13], "angle": 0,
		"totalTicks": 30, "activatorID": "button1", "active": false},
		{"width": 1, "height": 4, "pos": [24, 13], "angle": 0,
			"totalTicks": 30, "activatorID": "button1", "active": true}],
	"activators": [{"pos": [14, 12], "type": "button", "id" : "button1"}],
	"flamethrowers" : [{"pos": [5, 14], "pushable": true, "angle": 270}],
	"lasers" : [{"pos" :  [17, 12], "angle" : 90, "active":true}],
	"exits" : [{"type":  "return", "height": 18, "pos": [0, 9]},
		{"type":  "goal", "height": 18, "pos": [32, 9]}],
	"walls": 		[
		{"shape":[32.0, 18.0, 32.0, 17.0,  0, 17.0,0,18]},
		{"shape":[0, 15, 4, 15, 4, 0, 0, 0]},
		{"shape":[4, 13, 10, 13, 11, 12, 18, 12, 18, 13, 32, 13, 32, 0, 4, 0]}
			 		]
}